{
    "sounddata": [
        {
            "Sound_id": 104000,
            "Sound_name": "Title(Temp)",
            "Loop": true,
            "Desc": "배경음",
            "Sound_path": "Sounds/BGM/Title.mp3",
            "Volume": 1.0,
            "Pitch": 1.0
        },
        {
            "Sound_id": 104001,
            "Sound_name": "InGame(Temp)",
            "Loop": true,
            "Desc": "배경음",
            "Sound_path": "Sounds/BGM/InGame.mp3",
            "Volume": 1.0,
            "Pitch": 1.0
        },
        {
            "Sound_id": 104101,
            "Sound_name": "Sword_Fix",
            "Loop": false,
            "Desc": "평타1",
            "Sound_path": "Sounds/SFX/PlayerSFX/Sword_Fix.mp3",
            "Volume": 1.0,
            "Pitch": 1.0
        },
        {
            "Sound_id": 104102,
            "Sound_name": "Parry_Fix",
            "Loop": false,
            "Desc": "패링",
            "Sound_path": "Sounds/SFX/PlayerSFX/Parry_Fix.mp3",
            "Volume": 1.0,
            "Pitch": 1.0
        },
        {
            "Sound_id": 104103,
            "Sound_name": "Fury_Fix",
            "Loop": false,
            "Desc": "섬단",
            "Sound_path": "Sounds/SFX/PlayerSFX/Fury_Fix.mp3",
            "Volume": 1.0,
            "Pitch": 1.0
        },
        {
            "Sound_id": 104104,
            "Sound_name": "AirAtk",
            "Loop": false,
            "Desc": "공중공격",
            "Sound_path": "",
            "Volume": 1.0,
            "Pitch": 1.0
        },
        {
            "Sound_id": 104105,
            "Sound_name": "Stomp",
            "Loop": false,
            "Desc": "보스1:스톰프",
            "Sound_path": "",
            "Volume": 1.0,
            "Pitch": 1.0
        },
        {
            "Sound_id": 104106,
            "Sound_name": "Earthquake",
            "Loop": false,
            "Desc": "보스1:어스퀰",
            "Sound_path": "",
            "Volume": 1.0,
            "Pitch": 1.0
        },
        {
            "Sound_id": 104107,
            "Sound_name": "hurt1",
            "Loop": false,
            "Desc": "?",
            "Sound_path": "",
            "Volume": 1.0,
            "Pitch": 1.0
        },
        {
            "Sound_id": 104108,
            "Sound_name": "hurt2",
            "Loop": false,
            "Desc": "?",
            "Sound_path": "",
            "Volume": 1.0,
            "Pitch": 1.0
        },
        {
            "Sound_id": 104109,
            "Sound_name": "",
            "Loop": false,
            "Desc": "",
            "Sound_path": "",
            "Volume": 0.0,
            "Pitch": 0.0
        },
        {
            "Sound_id": 104110,
            "Sound_name": "",
            "Loop": false,
            "Desc": "",
            "Sound_path": "",
            "Volume": 0.0,
            "Pitch": 0.0
        },
        {
            "Sound_id": 104111,
            "Sound_name": "",
            "Loop": false,
            "Desc": "",
            "Sound_path": "",
            "Volume": 0.0,
            "Pitch": 0.0
        },
        {
            "Sound_id": 104112,
            "Sound_name": "",
            "Loop": false,
            "Desc": "",
            "Sound_path": "",
            "Volume": 0.0,
            "Pitch": 0.0
        },
        {
            "Sound_id": 104113,
            "Sound_name": "",
            "Loop": false,
            "Desc": "",
            "Sound_path": "",
            "Volume": 0.0,
            "Pitch": 0.0
        },
        {
            "Sound_id": 104114,
            "Sound_name": "",
            "Loop": false,
            "Desc": "",
            "Sound_path": "",
            "Volume": 0.0,
            "Pitch": 0.0
        },
        {
            "Sound_id": 104115,
            "Sound_name": "",
            "Loop": false,
            "Desc": "",
            "Sound_path": "",
            "Volume": 0.0,
            "Pitch": 0.0
        },
        {
            "Sound_id": 104116,
            "Sound_name": "",
            "Loop": false,
            "Desc": "",
            "Sound_path": "",
            "Volume": 0.0,
            "Pitch": 0.0
        },
        {
            "Sound_id": 104117,
            "Sound_name": "",
            "Loop": false,
            "Desc": "",
            "Sound_path": "",
            "Volume": 0.0,
            "Pitch": 0.0
        },
        {
            "Sound_id": 104118,
            "Sound_name": "",
            "Loop": false,
            "Desc": "",
            "Sound_path": "",
            "Volume": 0.0,
            "Pitch": 0.0
        },
        {
            "Sound_id": 104119,
            "Sound_name": "",
            "Loop": false,
            "Desc": "",
            "Sound_path": "",
            "Volume": 0.0,
            "Pitch": 0.0
        },
        {
            "Sound_id": 104120,
            "Sound_name": "",
            "Loop": false,
            "Desc": "",
            "Sound_path": "",
            "Volume": 0.0,
            "Pitch": 0.0
        },
        {
            "Sound_id": 104121,
            "Sound_name": "",
            "Loop": false,
            "Desc": "",
            "Sound_path": "",
            "Volume": 0.0,
            "Pitch": 0.0
        },
        {
            "Sound_id": 104122,
            "Sound_name": "",
            "Loop": false,
            "Desc": "",
            "Sound_path": "",
            "Volume": 0.0,
            "Pitch": 0.0
        },
        {
            "Sound_id": 104123,
            "Sound_name": "",
            "Loop": false,
            "Desc": "",
            "Sound_path": "",
            "Volume": 0.0,
            "Pitch": 0.0
        },
        {
            "Sound_id": 104124,
            "Sound_name": "",
            "Loop": false,
            "Desc": "",
            "Sound_path": "",
            "Volume": 0.0,
            "Pitch": 0.0
        }
    ]
}